molecupy/__init__.py
molecupy/access.py
molecupy/exceptions.py
molecupy/pdb.py
molecupy/pdbdatafile.py
molecupy/pdbfile.py
molecupy/residues.py
molecupy/structures.py
molecupy/converters/__init__.py
molecupy/converters/model2pdbdatafile.py
molecupy/converters/pdbdatafile2model.py
molecupy/converters/pdbdatafile2pdbfile.py
molecupy/converters/pdbfile2pdbdatafile.py
molecupy/pdb/__init__.py
molecupy/pdb/access.py
molecupy/pdb/pdb.py
molecupy/pdb/pdbdatafile.py
molecupy/pdb/pdbfile.py
molecupy/pdb/residues.py
molecupy/structures/__init__.py
molecupy/structures/atoms.py
molecupy/structures/chains.py
molecupy/structures/complexes.py
molecupy/structures/matrix.py
molecupy/structures/models.py
molecupy/structures/molecules.py
molecupy-1.1.0.dist-info/DESCRIPTION.rst
molecupy-1.1.0.dist-info/METADATA
molecupy-1.1.0.dist-info/RECORD
molecupy-1.1.0.dist-info/WHEEL
molecupy-1.1.0.dist-info/exceptions.py
molecupy-1.1.0.dist-info/metadata.json
molecupy-1.1.0.dist-info/top_level.txt
