Metadata-Version: 2.0
Name: molecupy
Version: 1.1.0
Summary: A Python molecular modeller with PDB parsing.
Home-page: https://molecupy.samireland.com
Author: Sam Ireland
Author-email: mail@samireland.com
License: MIT
Keywords: chemistry bioinformatics proteins biochemistry molecules
Platform: UNKNOWN
Classifier: Development Status :: 4 - Beta
Classifier: Intended Audience :: Science/Research
Classifier: License :: OSI Approved :: MIT License
Classifier: Topic :: Scientific/Engineering :: Chemistry
Classifier: Programming Language :: Python :: 3
Classifier: Programming Language :: Python :: 3.0
Classifier: Programming Language :: Python :: 3.1
Classifier: Programming Language :: Python :: 3.2
Classifier: Programming Language :: Python :: 3.3
Classifier: Programming Language :: Python :: 3.4
Classifier: Programming Language :: Python :: 3.5
Requires-Dist: omnicanvas
Requires-Dist: requests
